setup.py
test_probability/Binomialdistribution.py
test_probability/Gaussiandistribution.py
test_probability/Generaldistribution.py
test_probability/__init__.py
test_probability.egg-info/PKG-INFO
test_probability.egg-info/SOURCES.txt
test_probability.egg-info/dependency_links.txt
test_probability.egg-info/not-zip-safe
test_probability.egg-info/top_level.txt