Metadata-Version: 1.0
Name: test-probability
Version: 0.1
Summary: Gaussian and Binomial distributions
Home-page: UNKNOWN
Author: Ernitia Paramasari
Author-email: UNKNOWN
License: UNKNOWN
Platform: UNKNOWN
